lotusdesigns/__init__.py
lotusdesigns/_version.py
lotusdesigns/app.py
lotusdesigns/args.py
lotusdesigns/bl.py
lotusdesigns/config.py
lotusdesigns/photo.py
lotusdesigns/utils.py
lotusdesigns/skeleton/config.yml
lotusdesigns/skeleton/template.jpg
lotusdesigns/skeleton/template.json
lotusdesigns-0.0.3.dist-info/METADATA
lotusdesigns-0.0.3.dist-info/WHEEL
lotusdesigns-0.0.3.dist-info/entry_points.txt
lotusdesigns-0.0.3.dist-info/top_level.txt
lotusdesigns-0.0.3.dist-info/RECORD
