Metadata-Version: 2.1
Name: lotusdesigns
Version: 0.0.3
Summary: Utility for the lotusDesignPrints shop
Author-email: Kanelis Elias <e.kanelis@voidbuffer.com>
Maintainer-email: Kanelis Elias <e.kanelis@voidbuffer.com>
Project-URL: Homepage, https://pypi.org/project/lotusdesigns/
Keywords: image,photo,utility
Classifier: Development Status :: 3 - Alpha
Classifier: Programming Language :: Python :: 3
Classifier: Programming Language :: Python :: 3.10
Classifier: Topic :: Artistic Software
Requires-Python: >3.10
Requires-Dist: imageio ==2.32.0
Requires-Dist: numpy ==1.26.1
Requires-Dist: Pillow ==10.0.1
Requires-Dist: PyYAML ==6.0.1
Requires-Dist: xdg-base-dirs ==6.0.1
